[
null,
{"id":1,"expanded":true,"name":"Start-End_outside","order":1,"parentId":0,"scrollX":728,"scrollY":409.77777777777777},
{"id":2,"expanded":true,"name":"Hall","order":2,"parentId":0,"scrollX":728,"scrollY":409.77777777777777},
{"id":3,"expanded":false,"name":"K1","order":3,"parentId":2,"scrollX":728,"scrollY":409.77777777777777},
{"id":4,"expanded":false,"name":"Class","order":4,"parentId":2,"scrollX":728,"scrollY":409.77777777777777},
{"id":5,"expanded":true,"name":"Class-1Floor","order":5,"parentId":2,"scrollX":728,"scrollY":409.77777777777777},
{"id":6,"expanded":true,"name":"Class-4Floor","order":8,"parentId":2,"scrollX":728,"scrollY":409.77777777777777},
{"id":7,"expanded":false,"name":"B2","order":6,"parentId":5,"scrollX":728,"scrollY":409.77777777777777},
{"id":8,"expanded":false,"name":"B3","order":7,"parentId":5,"scrollX":728,"scrollY":409.77777777777777},
{"id":9,"expanded":true,"name":"B9","order":9,"parentId":6,"scrollX":728,"scrollY":409.77777777777777},
{"id":10,"expanded":false,"name":"B8","order":10,"parentId":6,"scrollX":728,"scrollY":409.77777777777777}
]